odoo/addons/easy_my_coop_loan_account_be/README.rst
odoo/addons/easy_my_coop_loan_account_be/__init__.py
odoo/addons/easy_my_coop_loan_account_be/__manifest__.py
odoo/addons/easy_my_coop_loan_account_be/demo/emc_loan_account_demo.xml
odoo/addons/easy_my_coop_loan_account_be/i18n/easy_my_coop_loan_account_be.pot
odoo/addons/easy_my_coop_loan_account_be/readme/CONTRIBUTORS.rst
odoo/addons/easy_my_coop_loan_account_be/readme/DESCRIPTION.rst
odoo/addons/easy_my_coop_loan_account_be/static/description/index.html
odoo12_addon_easy_my_coop_loan_account_be-12.0.1.0.0.99.dev4.dist-info/METADATA
odoo12_addon_easy_my_coop_loan_account_be-12.0.1.0.0.99.dev4.dist-info/WHEEL
odoo12_addon_easy_my_coop_loan_account_be-12.0.1.0.0.99.dev4.dist-info/top_level.txt
odoo12_addon_easy_my_coop_loan_account_be-12.0.1.0.0.99.dev4.dist-info/RECORD
